hamza/init.py
hamza-0.1.dist-info/METADATA
hamza-0.1.dist-info/WHEEL
hamza-0.1.dist-info/top_level.txt
hamza-0.1.dist-info/RECORD
