Metadata-Version: 2.1
Name: hamza
Version: 0.1
Summary: this is a package
Home-page: UNKNOWN
Author: Muhammad Hamza
Author-email: UNKNOWN
License: UNKNOWN
Platform: UNKNOWN
